{
    "description": "Bortolotti, G., Piani, M., Gullino, M., Franceschini, C., Mengoli, D., & Manfrini, L. (2024). OpenAcces_RGBD_apple_dataset (Version 1.2.0)",
    "tags": [],
    "size": {
        "height": 1080,
        "width": 1920
    },
    "objects": [
        {
            "id": 1418435485,
            "classId": 11855358,
            "description": "32",
            "geometryType": "rectangle",
            "labelerLogin": "Manually annotated",
            "createdAt": "2023-09-21T14:48:11.307Z",
            "updatedAt": "2024-04-05T19:24:20.236166",
            "tags": [],
            "classTitle": "apple_manual_annot",
            "points": {
                "exterior": [
                    [
                        1236,
                        26
                    ],
                    [
                        1294,
                        84
                    ]
                ],
                "interior": []
            }
        },
        {
            "id": 1418435486,
            "classId": 11855358,
            "description": "33",
            "geometryType": "rectangle",
            "labelerLogin": "Manually annotated",
            "createdAt": "2023-09-21T14:48:11.307Z",
            "updatedAt": "2024-04-05T19:24:20.236176",
            "tags": [],
            "classTitle": "apple_manual_annot",
            "points": {
                "exterior": [
                    [
                        1258,
                        216
                    ],
                    [
                        1313,
                        268
                    ]
                ],
                "interior": []
            }
        },
        {
            "id": 1418435487,
            "classId": 11855358,
            "description": "34",
            "geometryType": "rectangle",
            "labelerLogin": "Manually annotated",
            "createdAt": "2023-09-21T14:48:11.307Z",
            "updatedAt": "2024-04-05T19:24:20.236183",
            "tags": [],
            "classTitle": "apple_manual_annot",
            "points": {
                "exterior": [
                    [
                        1474,
                        962
                    ],
                    [
                        1528,
                        1012
                    ]
                ],
                "interior": []
            }
        },
        {
            "id": 1418435488,
            "classId": 11855358,
            "description": "35",
            "geometryType": "rectangle",
            "labelerLogin": "Manually annotated",
            "createdAt": "2023-09-21T14:48:11.307Z",
            "updatedAt": "2024-04-05T19:24:20.236190",
            "tags": [],
            "classTitle": "apple_manual_annot",
            "points": {
                "exterior": [
                    [
                        1047,
                        451
                    ],
                    [
                        1093,
                        493
                    ]
                ],
                "interior": []
            }
        },
        {
            "id": 1418435489,
            "classId": 11855358,
            "description": "36",
            "geometryType": "rectangle",
            "labelerLogin": "Manually annotated",
            "createdAt": "2023-09-21T14:48:11.307Z",
            "updatedAt": "2024-04-05T19:24:20.236197",
            "tags": [],
            "classTitle": "apple_manual_annot",
            "points": {
                "exterior": [
                    [
                        1033,
                        668
                    ],
                    [
                        1081,
                        718
                    ]
                ],
                "interior": []
            }
        },
        {
            "id": 1418435490,
            "classId": 11855358,
            "description": "37",
            "geometryType": "rectangle",
            "labelerLogin": "Manually annotated",
            "createdAt": "2023-09-21T14:48:11.307Z",
            "updatedAt": "2024-04-05T19:24:20.236203",
            "tags": [],
            "classTitle": "apple_manual_annot",
            "points": {
                "exterior": [
                    [
                        993,
                        843
                    ],
                    [
                        1036,
                        886
                    ]
                ],
                "interior": []
            }
        },
        {
            "id": 1418435491,
            "classId": 11855358,
            "description": "38",
            "geometryType": "rectangle",
            "labelerLogin": "Manually annotated",
            "createdAt": "2023-09-21T14:48:11.307Z",
            "updatedAt": "2024-04-05T19:24:20.236210",
            "tags": [],
            "classTitle": "apple_manual_annot",
            "points": {
                "exterior": [
                    [
                        1025,
                        932
                    ],
                    [
                        1075,
                        983
                    ]
                ],
                "interior": []
            }
        },
        {
            "id": 1418435492,
            "classId": 11855358,
            "description": "39",
            "geometryType": "rectangle",
            "labelerLogin": "Manually annotated",
            "createdAt": "2023-09-21T14:48:11.307Z",
            "updatedAt": "2024-04-05T19:24:20.236216",
            "tags": [],
            "classTitle": "apple_manual_annot",
            "points": {
                "exterior": [
                    [
                        726,
                        668
                    ],
                    [
                        772,
                        712
                    ]
                ],
                "interior": []
            }
        },
        {
            "id": 1418435493,
            "classId": 11855358,
            "description": "40",
            "geometryType": "rectangle",
            "labelerLogin": "Manually annotated",
            "createdAt": "2023-09-21T14:48:11.307Z",
            "updatedAt": "2024-04-05T19:24:20.236223",
            "tags": [],
            "classTitle": "apple_manual_annot",
            "points": {
                "exterior": [
                    [
                        713,
                        819
                    ],
                    [
                        758,
                        868
                    ]
                ],
                "interior": []
            }
        },
        {
            "id": 1418435496,
            "classId": 11855358,
            "description": "43",
            "geometryType": "rectangle",
            "labelerLogin": "Manually annotated",
            "createdAt": "2023-09-21T14:48:11.307Z",
            "updatedAt": "2024-04-05T19:24:20.236230",
            "tags": [],
            "classTitle": "apple_manual_annot",
            "points": {
                "exterior": [
                    [
                        418,
                        809
                    ],
                    [
                        465,
                        855
                    ]
                ],
                "interior": []
            }
        },
        {
            "id": 1418435495,
            "classId": 11855358,
            "description": "42",
            "geometryType": "rectangle",
            "labelerLogin": "Manually annotated",
            "createdAt": "2023-09-21T14:48:11.307Z",
            "updatedAt": "2024-04-05T19:24:20.236236",
            "tags": [],
            "classTitle": "apple_manual_annot",
            "points": {
                "exterior": [
                    [
                        400,
                        466
                    ],
                    [
                        456,
                        519
                    ]
                ],
                "interior": []
            }
        },
        {
            "id": 1418435494,
            "classId": 11855358,
            "description": "41",
            "geometryType": "rectangle",
            "labelerLogin": "Manually annotated",
            "createdAt": "2023-09-21T14:48:11.307Z",
            "updatedAt": "2024-04-05T19:24:20.236243",
            "tags": [],
            "classTitle": "apple_manual_annot",
            "points": {
                "exterior": [
                    [
                        446,
                        111
                    ],
                    [
                        496,
                        153
                    ]
                ],
                "interior": []
            }
        },
        {
            "id": 1418438241,
            "classId": 11855360,
            "description": "",
            "geometryType": "rectangle",
            "labelerLogin": "Item annotated with a YOLOv5l standard model from ultralytics",
            "createdAt": "2023-09-21T14:49:03.399Z",
            "updatedAt": "2024-04-05T19:24:20.236250",
            "tags": [],
            "classTitle": "apple_Y5L_std_bbox",
            "points": {
                "exterior": [
                    [
                        1543,
                        364
                    ],
                    [
                        1584,
                        407
                    ]
                ],
                "interior": []
            }
        },
        {
            "id": 1418438240,
            "classId": 11855360,
            "description": "",
            "geometryType": "rectangle",
            "labelerLogin": "Item annotated with a YOLOv5l standard model from ultralytics",
            "createdAt": "2023-09-21T14:49:03.399Z",
            "updatedAt": "2024-04-05T19:24:20.236256",
            "tags": [],
            "classTitle": "apple_Y5L_std_bbox",
            "points": {
                "exterior": [
                    [
                        1741,
                        135
                    ],
                    [
                        1786,
                        189
                    ]
                ],
                "interior": []
            }
        },
        {
            "id": 1418438239,
            "classId": 11855360,
            "description": "",
            "geometryType": "rectangle",
            "labelerLogin": "Item annotated with a YOLOv5l standard model from ultralytics",
            "createdAt": "2023-09-21T14:49:03.399Z",
            "updatedAt": "2024-04-05T19:24:20.236262",
            "tags": [],
            "classTitle": "apple_Y5L_std_bbox",
            "points": {
                "exterior": [
                    [
                        346,
                        187
                    ],
                    [
                        370,
                        226
                    ]
                ],
                "interior": []
            }
        },
        {
            "id": 1418438238,
            "classId": 11855360,
            "description": "",
            "geometryType": "rectangle",
            "labelerLogin": "Item annotated with a YOLOv5l standard model from ultralytics",
            "createdAt": "2023-09-21T14:49:03.399Z",
            "updatedAt": "2024-04-05T19:24:20.236268",
            "tags": [],
            "classTitle": "apple_Y5L_std_bbox",
            "points": {
                "exterior": [
                    [
                        1898,
                        888
                    ],
                    [
                        1919,
                        919
                    ]
                ],
                "interior": []
            }
        },
        {
            "id": 1418438237,
            "classId": 11855360,
            "description": "",
            "geometryType": "rectangle",
            "labelerLogin": "Item annotated with a YOLOv5l standard model from ultralytics",
            "createdAt": "2023-09-21T14:49:03.399Z",
            "updatedAt": "2024-04-05T19:24:20.236275",
            "tags": [],
            "classTitle": "apple_Y5L_std_bbox",
            "points": {
                "exterior": [
                    [
                        1722,
                        209
                    ],
                    [
                        1767,
                        251
                    ]
                ],
                "interior": []
            }
        },
        {
            "id": 1418438236,
            "classId": 11855360,
            "description": "",
            "geometryType": "rectangle",
            "labelerLogin": "Item annotated with a YOLOv5l standard model from ultralytics",
            "createdAt": "2023-09-21T14:49:03.399Z",
            "updatedAt": "2024-04-05T19:24:20.236281",
            "tags": [],
            "classTitle": "apple_Y5L_std_bbox",
            "points": {
                "exterior": [
                    [
                        569,
                        805
                    ],
                    [
                        609,
                        846
                    ]
                ],
                "interior": []
            }
        },
        {
            "id": 1418438235,
            "classId": 11855360,
            "description": "",
            "geometryType": "rectangle",
            "labelerLogin": "Item annotated with a YOLOv5l standard model from ultralytics",
            "createdAt": "2023-09-21T14:49:03.399Z",
            "updatedAt": "2024-04-05T19:24:20.236287",
            "tags": [],
            "classTitle": "apple_Y5L_std_bbox",
            "points": {
                "exterior": [
                    [
                        1583,
                        117
                    ],
                    [
                        1631,
                        166
                    ]
                ],
                "interior": []
            }
        },
        {
            "id": 1418438234,
            "classId": 11855360,
            "description": "41",
            "geometryType": "rectangle",
            "labelerLogin": "Item annotated with a YOLOv5l standard model from ultralytics",
            "createdAt": "2023-09-21T14:49:03.399Z",
            "updatedAt": "2024-04-05T19:24:20.236293",
            "tags": [],
            "classTitle": "apple_Y5L_std_bbox",
            "points": {
                "exterior": [
                    [
                        453,
                        110
                    ],
                    [
                        495,
                        152
                    ]
                ],
                "interior": []
            }
        },
        {
            "id": 1418438233,
            "classId": 11855360,
            "description": "43",
            "geometryType": "rectangle",
            "labelerLogin": "Item annotated with a YOLOv5l standard model from ultralytics",
            "createdAt": "2023-09-21T14:49:03.399Z",
            "updatedAt": "2024-04-05T19:24:20.236300",
            "tags": [],
            "classTitle": "apple_Y5L_std_bbox",
            "points": {
                "exterior": [
                    [
                        418,
                        811
                    ],
                    [
                        467,
                        853
                    ]
                ],
                "interior": []
            }
        },
        {
            "id": 1418438232,
            "classId": 11855360,
            "description": "",
            "geometryType": "rectangle",
            "labelerLogin": "Item annotated with a YOLOv5l standard model from ultralytics",
            "createdAt": "2023-09-21T14:49:03.399Z",
            "updatedAt": "2024-04-05T19:24:20.236306",
            "tags": [],
            "classTitle": "apple_Y5L_std_bbox",
            "points": {
                "exterior": [
                    [
                        559,
                        753
                    ],
                    [
                        604,
                        789
                    ]
                ],
                "interior": []
            }
        },
        {
            "id": 1418438231,
            "classId": 11855360,
            "description": "37",
            "geometryType": "rectangle",
            "labelerLogin": "Item annotated with a YOLOv5l standard model from ultralytics",
            "createdAt": "2023-09-21T14:49:03.399Z",
            "updatedAt": "2024-04-05T19:24:20.236313",
            "tags": [],
            "classTitle": "apple_Y5L_std_bbox",
            "points": {
                "exterior": [
                    [
                        994,
                        843
                    ],
                    [
                        1035,
                        884
                    ]
                ],
                "interior": []
            }
        },
        {
            "id": 1418438230,
            "classId": 11855360,
            "description": "",
            "geometryType": "rectangle",
            "labelerLogin": "Item annotated with a YOLOv5l standard model from ultralytics",
            "createdAt": "2023-09-21T14:49:03.399Z",
            "updatedAt": "2024-04-05T19:24:20.236319",
            "tags": [],
            "classTitle": "apple_Y5L_std_bbox",
            "points": {
                "exterior": [
                    [
                        129,
                        118
                    ],
                    [
                        185,
                        168
                    ]
                ],
                "interior": []
            }
        },
        {
            "id": 1418438229,
            "classId": 11855360,
            "description": "33",
            "geometryType": "rectangle",
            "labelerLogin": "Item annotated with a YOLOv5l standard model from ultralytics",
            "createdAt": "2023-09-21T14:49:03.399Z",
            "updatedAt": "2024-04-05T19:24:20.236325",
            "tags": [],
            "classTitle": "apple_Y5L_std_bbox",
            "points": {
                "exterior": [
                    [
                        1260,
                        215
                    ],
                    [
                        1313,
                        266
                    ]
                ],
                "interior": []
            }
        },
        {
            "id": 1418438228,
            "classId": 11855360,
            "description": "",
            "geometryType": "rectangle",
            "labelerLogin": "Item annotated with a YOLOv5l standard model from ultralytics",
            "createdAt": "2023-09-21T14:49:03.399Z",
            "updatedAt": "2024-04-05T19:24:20.236332",
            "tags": [],
            "classTitle": "apple_Y5L_std_bbox",
            "points": {
                "exterior": [
                    [
                        507,
                        653
                    ],
                    [
                        553,
                        700
                    ]
                ],
                "interior": []
            }
        },
        {
            "id": 1418438227,
            "classId": 11855360,
            "description": "",
            "geometryType": "rectangle",
            "labelerLogin": "Item annotated with a YOLOv5l standard model from ultralytics",
            "createdAt": "2023-09-21T14:49:03.399Z",
            "updatedAt": "2024-04-05T19:24:20.236338",
            "tags": [],
            "classTitle": "apple_Y5L_std_bbox",
            "points": {
                "exterior": [
                    [
                        366,
                        163
                    ],
                    [
                        418,
                        213
                    ]
                ],
                "interior": []
            }
        },
        {
            "id": 1418438226,
            "classId": 11855360,
            "description": "32",
            "geometryType": "rectangle",
            "labelerLogin": "Item annotated with a YOLOv5l standard model from ultralytics",
            "createdAt": "2023-09-21T14:49:03.399Z",
            "updatedAt": "2024-04-05T19:24:20.236344",
            "tags": [],
            "classTitle": "apple_Y5L_std_bbox",
            "points": {
                "exterior": [
                    [
                        1238,
                        27
                    ],
                    [
                        1293,
                        87
                    ]
                ],
                "interior": []
            }
        },
        {
            "id": 1418438225,
            "classId": 11855360,
            "description": "38",
            "geometryType": "rectangle",
            "labelerLogin": "Item annotated with a YOLOv5l standard model from ultralytics",
            "createdAt": "2023-09-21T14:49:03.399Z",
            "updatedAt": "2024-04-05T19:24:20.236351",
            "tags": [],
            "classTitle": "apple_Y5L_std_bbox",
            "points": {
                "exterior": [
                    [
                        1027,
                        934
                    ],
                    [
                        1074,
                        981
                    ]
                ],
                "interior": []
            }
        },
        {
            "id": 1418438224,
            "classId": 11855360,
            "description": "",
            "geometryType": "rectangle",
            "labelerLogin": "Item annotated with a YOLOv5l standard model from ultralytics",
            "createdAt": "2023-09-21T14:49:03.399Z",
            "updatedAt": "2024-04-05T19:24:20.236357",
            "tags": [],
            "classTitle": "apple_Y5L_std_bbox",
            "points": {
                "exterior": [
                    [
                        1003,
                        991
                    ],
                    [
                        1049,
                        1044
                    ]
                ],
                "interior": []
            }
        },
        {
            "id": 1418438223,
            "classId": 11855360,
            "description": "",
            "geometryType": "rectangle",
            "labelerLogin": "Item annotated with a YOLOv5l standard model from ultralytics",
            "createdAt": "2023-09-21T14:49:03.399Z",
            "updatedAt": "2024-04-05T19:24:20.236363",
            "tags": [],
            "classTitle": "apple_Y5L_std_bbox",
            "points": {
                "exterior": [
                    [
                        1139,
                        195
                    ],
                    [
                        1183,
                        239
                    ]
                ],
                "interior": []
            }
        },
        {
            "id": 1418438222,
            "classId": 11855360,
            "description": "",
            "geometryType": "rectangle",
            "labelerLogin": "Item annotated with a YOLOv5l standard model from ultralytics",
            "createdAt": "2023-09-21T14:49:03.399Z",
            "updatedAt": "2024-04-05T19:24:20.236369",
            "tags": [],
            "classTitle": "apple_Y5L_std_bbox",
            "points": {
                "exterior": [
                    [
                        1095,
                        434
                    ],
                    [
                        1135,
                        474
                    ]
                ],
                "interior": []
            }
        },
        {
            "id": 1418438221,
            "classId": 11855360,
            "description": "",
            "geometryType": "rectangle",
            "labelerLogin": "Item annotated with a YOLOv5l standard model from ultralytics",
            "createdAt": "2023-09-21T14:49:03.399Z",
            "updatedAt": "2024-04-05T19:24:20.236376",
            "tags": [],
            "classTitle": "apple_Y5L_std_bbox",
            "points": {
                "exterior": [
                    [
                        342,
                        119
                    ],
                    [
                        399,
                        167
                    ]
                ],
                "interior": []
            }
        },
        {
            "id": 1418438220,
            "classId": 11855360,
            "description": "",
            "geometryType": "rectangle",
            "labelerLogin": "Item annotated with a YOLOv5l standard model from ultralytics",
            "createdAt": "2023-09-21T14:49:03.399Z",
            "updatedAt": "2024-04-05T19:24:20.236382",
            "tags": [],
            "classTitle": "apple_Y5L_std_bbox",
            "points": {
                "exterior": [
                    [
                        1173,
                        212
                    ],
                    [
                        1219,
                        260
                    ]
                ],
                "interior": []
            }
        },
        {
            "id": 1418438219,
            "classId": 11855360,
            "description": "",
            "geometryType": "rectangle",
            "labelerLogin": "Item annotated with a YOLOv5l standard model from ultralytics",
            "createdAt": "2023-09-21T14:49:03.399Z",
            "updatedAt": "2024-04-05T19:24:20.236388",
            "tags": [],
            "classTitle": "apple_Y5L_std_bbox",
            "points": {
                "exterior": [
                    [
                        1536,
                        174
                    ],
                    [
                        1590,
                        228
                    ]
                ],
                "interior": []
            }
        },
        {
            "id": 1418438218,
            "classId": 11855360,
            "description": "",
            "geometryType": "rectangle",
            "labelerLogin": "Item annotated with a YOLOv5l standard model from ultralytics",
            "createdAt": "2023-09-21T14:49:03.399Z",
            "updatedAt": "2024-04-05T19:24:20.236394",
            "tags": [],
            "classTitle": "apple_Y5L_std_bbox",
            "points": {
                "exterior": [
                    [
                        1639,
                        638
                    ],
                    [
                        1686,
                        681
                    ]
                ],
                "interior": []
            }
        },
        {
            "id": 1418438217,
            "classId": 11855360,
            "description": "",
            "geometryType": "rectangle",
            "labelerLogin": "Item annotated with a YOLOv5l standard model from ultralytics",
            "createdAt": "2023-09-21T14:49:03.399Z",
            "updatedAt": "2024-04-05T19:24:20.236400",
            "tags": [],
            "classTitle": "apple_Y5L_std_bbox",
            "points": {
                "exterior": [
                    [
                        1499,
                        474
                    ],
                    [
                        1549,
                        521
                    ]
                ],
                "interior": []
            }
        },
        {
            "id": 1418438216,
            "classId": 11855360,
            "description": "",
            "geometryType": "rectangle",
            "labelerLogin": "Item annotated with a YOLOv5l standard model from ultralytics",
            "createdAt": "2023-09-21T14:49:03.399Z",
            "updatedAt": "2024-04-05T19:24:20.236407",
            "tags": [],
            "classTitle": "apple_Y5L_std_bbox",
            "points": {
                "exterior": [
                    [
                        432,
                        603
                    ],
                    [
                        483,
                        647
                    ]
                ],
                "interior": []
            }
        },
        {
            "id": 1418438215,
            "classId": 11855360,
            "description": "",
            "geometryType": "rectangle",
            "labelerLogin": "Item annotated with a YOLOv5l standard model from ultralytics",
            "createdAt": "2023-09-21T14:49:03.399Z",
            "updatedAt": "2024-04-05T19:24:20.236413",
            "tags": [],
            "classTitle": "apple_Y5L_std_bbox",
            "points": {
                "exterior": [
                    [
                        602,
                        778
                    ],
                    [
                        652,
                        832
                    ]
                ],
                "interior": []
            }
        },
        {
            "id": 1418438214,
            "classId": 11855360,
            "description": "42",
            "geometryType": "rectangle",
            "labelerLogin": "Item annotated with a YOLOv5l standard model from ultralytics",
            "createdAt": "2023-09-21T14:49:03.399Z",
            "updatedAt": "2024-04-05T19:24:20.236419",
            "tags": [],
            "classTitle": "apple_Y5L_std_bbox",
            "points": {
                "exterior": [
                    [
                        400,
                        467
                    ],
                    [
                        453,
                        520
                    ]
                ],
                "interior": []
            }
        },
        {
            "id": 1418438213,
            "classId": 11855360,
            "description": "35",
            "geometryType": "rectangle",
            "labelerLogin": "Item annotated with a YOLOv5l standard model from ultralytics",
            "createdAt": "2023-09-21T14:49:03.399Z",
            "updatedAt": "2024-04-05T19:24:20.236426",
            "tags": [],
            "classTitle": "apple_Y5L_std_bbox",
            "points": {
                "exterior": [
                    [
                        1050,
                        451
                    ],
                    [
                        1090,
                        489
                    ]
                ],
                "interior": []
            }
        },
        {
            "id": 1418438212,
            "classId": 11855360,
            "description": "39",
            "geometryType": "rectangle",
            "labelerLogin": "Item annotated with a YOLOv5l standard model from ultralytics",
            "createdAt": "2023-09-21T14:49:03.399Z",
            "updatedAt": "2024-04-05T19:24:20.236432",
            "tags": [],
            "classTitle": "apple_Y5L_std_bbox",
            "points": {
                "exterior": [
                    [
                        728,
                        668
                    ],
                    [
                        774,
                        711
                    ]
                ],
                "interior": []
            }
        },
        {
            "id": 1418438211,
            "classId": 11855360,
            "description": "",
            "geometryType": "rectangle",
            "labelerLogin": "Item annotated with a YOLOv5l standard model from ultralytics",
            "createdAt": "2023-09-21T14:49:03.399Z",
            "updatedAt": "2024-04-05T19:24:20.236438",
            "tags": [],
            "classTitle": "apple_Y5L_std_bbox",
            "points": {
                "exterior": [
                    [
                        1600,
                        621
                    ],
                    [
                        1649,
                        666
                    ]
                ],
                "interior": []
            }
        },
        {
            "id": 1418438210,
            "classId": 11855360,
            "description": "36",
            "geometryType": "rectangle",
            "labelerLogin": "Item annotated with a YOLOv5l standard model from ultralytics",
            "createdAt": "2023-09-21T14:49:03.399Z",
            "updatedAt": "2024-04-05T19:24:20.236445",
            "tags": [],
            "classTitle": "apple_Y5L_std_bbox",
            "points": {
                "exterior": [
                    [
                        1034,
                        671
                    ],
                    [
                        1080,
                        717
                    ]
                ],
                "interior": []
            }
        },
        {
            "id": 1418440145,
            "classId": 11855359,
            "description": "",
            "geometryType": "rectangle",
            "labelerLogin": "Item annotated with a YOLOv5l model from ultralytics trained on a custom dataset",
            "createdAt": "2023-09-21T14:49:32.964Z",
            "updatedAt": "2024-04-05T19:24:20.236451",
            "tags": [],
            "classTitle": "apple_Y5L_trained_bbox",
            "points": {
                "exterior": [
                    [
                        1641,
                        638
                    ],
                    [
                        1683,
                        682
                    ]
                ],
                "interior": []
            }
        },
        {
            "id": 1418440144,
            "classId": 11855359,
            "description": "",
            "geometryType": "rectangle",
            "labelerLogin": "Item annotated with a YOLOv5l model from ultralytics trained on a custom dataset",
            "createdAt": "2023-09-21T14:49:32.964Z",
            "updatedAt": "2024-04-05T19:24:20.236458",
            "tags": [],
            "classTitle": "apple_Y5L_trained_bbox",
            "points": {
                "exterior": [
                    [
                        1725,
                        212
                    ],
                    [
                        1766,
                        250
                    ]
                ],
                "interior": []
            }
        },
        {
            "id": 1418440143,
            "classId": 11855359,
            "description": "",
            "geometryType": "rectangle",
            "labelerLogin": "Item annotated with a YOLOv5l model from ultralytics trained on a custom dataset",
            "createdAt": "2023-09-21T14:49:32.964Z",
            "updatedAt": "2024-04-05T19:24:20.236464",
            "tags": [],
            "classTitle": "apple_Y5L_trained_bbox",
            "points": {
                "exterior": [
                    [
                        1543,
                        365
                    ],
                    [
                        1583,
                        407
                    ]
                ],
                "interior": []
            }
        },
        {
            "id": 1418440142,
            "classId": 11855359,
            "description": "",
            "geometryType": "rectangle",
            "labelerLogin": "Item annotated with a YOLOv5l model from ultralytics trained on a custom dataset",
            "createdAt": "2023-09-21T14:49:32.964Z",
            "updatedAt": "2024-04-05T19:24:20.236470",
            "tags": [],
            "classTitle": "apple_Y5L_trained_bbox",
            "points": {
                "exterior": [
                    [
                        193,
                        815
                    ],
                    [
                        238,
                        857
                    ]
                ],
                "interior": []
            }
        },
        {
            "id": 1418440141,
            "classId": 11855359,
            "description": "39",
            "geometryType": "rectangle",
            "labelerLogin": "Item annotated with a YOLOv5l model from ultralytics trained on a custom dataset",
            "createdAt": "2023-09-21T14:49:32.964Z",
            "updatedAt": "2024-04-05T19:24:20.236477",
            "tags": [],
            "classTitle": "apple_Y5L_trained_bbox",
            "points": {
                "exterior": [
                    [
                        729,
                        670
                    ],
                    [
                        772,
                        711
                    ]
                ],
                "interior": []
            }
        },
        {
            "id": 1418440140,
            "classId": 11855359,
            "description": "",
            "geometryType": "rectangle",
            "labelerLogin": "Item annotated with a YOLOv5l model from ultralytics trained on a custom dataset",
            "createdAt": "2023-09-21T14:49:32.964Z",
            "updatedAt": "2024-04-05T19:24:20.236483",
            "tags": [],
            "classTitle": "apple_Y5L_trained_bbox",
            "points": {
                "exterior": [
                    [
                        1232,
                        0
                    ],
                    [
                        1282,
                        17
                    ]
                ],
                "interior": []
            }
        },
        {
            "id": 1418440139,
            "classId": 11855359,
            "description": "",
            "geometryType": "rectangle",
            "labelerLogin": "Item annotated with a YOLOv5l model from ultralytics trained on a custom dataset",
            "createdAt": "2023-09-21T14:49:32.964Z",
            "updatedAt": "2024-04-05T19:24:20.236490",
            "tags": [],
            "classTitle": "apple_Y5L_trained_bbox",
            "points": {
                "exterior": [
                    [
                        1540,
                        174
                    ],
                    [
                        1589,
                        225
                    ]
                ],
                "interior": []
            }
        },
        {
            "id": 1418440138,
            "classId": 11855359,
            "description": "",
            "geometryType": "rectangle",
            "labelerLogin": "Item annotated with a YOLOv5l model from ultralytics trained on a custom dataset",
            "createdAt": "2023-09-21T14:49:32.964Z",
            "updatedAt": "2024-04-05T19:24:20.236496",
            "tags": [],
            "classTitle": "apple_Y5L_trained_bbox",
            "points": {
                "exterior": [
                    [
                        562,
                        754
                    ],
                    [
                        603,
                        791
                    ]
                ],
                "interior": []
            }
        },
        {
            "id": 1418440137,
            "classId": 11855359,
            "description": "",
            "geometryType": "rectangle",
            "labelerLogin": "Item annotated with a YOLOv5l model from ultralytics trained on a custom dataset",
            "createdAt": "2023-09-21T14:49:32.964Z",
            "updatedAt": "2024-04-05T19:24:20.236502",
            "tags": [],
            "classTitle": "apple_Y5L_trained_bbox",
            "points": {
                "exterior": [
                    [
                        55,
                        762
                    ],
                    [
                        98,
                        802
                    ]
                ],
                "interior": []
            }
        },
        {
            "id": 1418440136,
            "classId": 11855359,
            "description": "",
            "geometryType": "rectangle",
            "labelerLogin": "Item annotated with a YOLOv5l model from ultralytics trained on a custom dataset",
            "createdAt": "2023-09-21T14:49:32.964Z",
            "updatedAt": "2024-04-05T19:24:20.236509",
            "tags": [],
            "classTitle": "apple_Y5L_trained_bbox",
            "points": {
                "exterior": [
                    [
                        1174,
                        215
                    ],
                    [
                        1218,
                        259
                    ]
                ],
                "interior": []
            }
        },
        {
            "id": 1418440135,
            "classId": 11855359,
            "description": "",
            "geometryType": "rectangle",
            "labelerLogin": "Item annotated with a YOLOv5l model from ultralytics trained on a custom dataset",
            "createdAt": "2023-09-21T14:49:32.964Z",
            "updatedAt": "2024-04-05T19:24:20.236515",
            "tags": [],
            "classTitle": "apple_Y5L_trained_bbox",
            "points": {
                "exterior": [
                    [
                        509,
                        654
                    ],
                    [
                        551,
                        697
                    ]
                ],
                "interior": []
            }
        },
        {
            "id": 1418440134,
            "classId": 11855359,
            "description": "",
            "geometryType": "rectangle",
            "labelerLogin": "Item annotated with a YOLOv5l model from ultralytics trained on a custom dataset",
            "createdAt": "2023-09-21T14:49:32.964Z",
            "updatedAt": "2024-04-05T19:24:20.236522",
            "tags": [],
            "classTitle": "apple_Y5L_trained_bbox",
            "points": {
                "exterior": [
                    [
                        1139,
                        197
                    ],
                    [
                        1182,
                        237
                    ]
                ],
                "interior": []
            }
        },
        {
            "id": 1418440133,
            "classId": 11855359,
            "description": "41",
            "geometryType": "rectangle",
            "labelerLogin": "Item annotated with a YOLOv5l model from ultralytics trained on a custom dataset",
            "createdAt": "2023-09-21T14:49:32.964Z",
            "updatedAt": "2024-04-05T19:24:20.236528",
            "tags": [],
            "classTitle": "apple_Y5L_trained_bbox",
            "points": {
                "exterior": [
                    [
                        448,
                        110
                    ],
                    [
                        494,
                        154
                    ]
                ],
                "interior": []
            }
        },
        {
            "id": 1418440132,
            "classId": 11855359,
            "description": "33",
            "geometryType": "rectangle",
            "labelerLogin": "Item annotated with a YOLOv5l model from ultralytics trained on a custom dataset",
            "createdAt": "2023-09-21T14:49:32.964Z",
            "updatedAt": "2024-04-05T19:24:20.236535",
            "tags": [],
            "classTitle": "apple_Y5L_trained_bbox",
            "points": {
                "exterior": [
                    [
                        1264,
                        219
                    ],
                    [
                        1309,
                        264
                    ]
                ],
                "interior": []
            }
        },
        {
            "id": 1418440131,
            "classId": 11855359,
            "description": "",
            "geometryType": "rectangle",
            "labelerLogin": "Item annotated with a YOLOv5l model from ultralytics trained on a custom dataset",
            "createdAt": "2023-09-21T14:49:32.964Z",
            "updatedAt": "2024-04-05T19:24:20.236541",
            "tags": [],
            "classTitle": "apple_Y5L_trained_bbox",
            "points": {
                "exterior": [
                    [
                        436,
                        602
                    ],
                    [
                        482,
                        647
                    ]
                ],
                "interior": []
            }
        },
        {
            "id": 1418440130,
            "classId": 11855359,
            "description": "",
            "geometryType": "rectangle",
            "labelerLogin": "Item annotated with a YOLOv5l model from ultralytics trained on a custom dataset",
            "createdAt": "2023-09-21T14:49:32.964Z",
            "updatedAt": "2024-04-05T19:24:20.236548",
            "tags": [],
            "classTitle": "apple_Y5L_trained_bbox",
            "points": {
                "exterior": [
                    [
                        1600,
                        622
                    ],
                    [
                        1646,
                        665
                    ]
                ],
                "interior": []
            }
        },
        {
            "id": 1418440129,
            "classId": 11855359,
            "description": "38",
            "geometryType": "rectangle",
            "labelerLogin": "Item annotated with a YOLOv5l model from ultralytics trained on a custom dataset",
            "createdAt": "2023-09-21T14:49:32.964Z",
            "updatedAt": "2024-04-05T19:24:20.236554",
            "tags": [],
            "classTitle": "apple_Y5L_trained_bbox",
            "points": {
                "exterior": [
                    [
                        1027,
                        934
                    ],
                    [
                        1073,
                        980
                    ]
                ],
                "interior": []
            }
        },
        {
            "id": 1418440128,
            "classId": 11855359,
            "description": "",
            "geometryType": "rectangle",
            "labelerLogin": "Item annotated with a YOLOv5l model from ultralytics trained on a custom dataset",
            "createdAt": "2023-09-21T14:49:32.964Z",
            "updatedAt": "2024-04-05T19:24:20.236561",
            "tags": [],
            "classTitle": "apple_Y5L_trained_bbox",
            "points": {
                "exterior": [
                    [
                        346,
                        122
                    ],
                    [
                        398,
                        168
                    ]
                ],
                "interior": []
            }
        },
        {
            "id": 1418440127,
            "classId": 11855359,
            "description": "43",
            "geometryType": "rectangle",
            "labelerLogin": "Item annotated with a YOLOv5l model from ultralytics trained on a custom dataset",
            "createdAt": "2023-09-21T14:49:32.964Z",
            "updatedAt": "2024-04-05T19:24:20.236567",
            "tags": [],
            "classTitle": "apple_Y5L_trained_bbox",
            "points": {
                "exterior": [
                    [
                        421,
                        812
                    ],
                    [
                        464,
                        854
                    ]
                ],
                "interior": []
            }
        },
        {
            "id": 1418440126,
            "classId": 11855359,
            "description": "",
            "geometryType": "rectangle",
            "labelerLogin": "Item annotated with a YOLOv5l model from ultralytics trained on a custom dataset",
            "createdAt": "2023-09-21T14:49:32.964Z",
            "updatedAt": "2024-04-05T19:24:20.236574",
            "tags": [],
            "classTitle": "apple_Y5L_trained_bbox",
            "points": {
                "exterior": [
                    [
                        367,
                        164
                    ],
                    [
                        417,
                        216
                    ]
                ],
                "interior": []
            }
        },
        {
            "id": 1418440125,
            "classId": 11855359,
            "description": "",
            "geometryType": "rectangle",
            "labelerLogin": "Item annotated with a YOLOv5l model from ultralytics trained on a custom dataset",
            "createdAt": "2023-09-21T14:49:32.964Z",
            "updatedAt": "2024-04-05T19:24:20.236580",
            "tags": [],
            "classTitle": "apple_Y5L_trained_bbox",
            "points": {
                "exterior": [
                    [
                        1003,
                        992
                    ],
                    [
                        1047,
                        1040
                    ]
                ],
                "interior": []
            }
        },
        {
            "id": 1418440124,
            "classId": 11855359,
            "description": "",
            "geometryType": "rectangle",
            "labelerLogin": "Item annotated with a YOLOv5l model from ultralytics trained on a custom dataset",
            "createdAt": "2023-09-21T14:49:32.964Z",
            "updatedAt": "2024-04-05T19:24:20.236587",
            "tags": [],
            "classTitle": "apple_Y5L_trained_bbox",
            "points": {
                "exterior": [
                    [
                        603,
                        780
                    ],
                    [
                        650,
                        828
                    ]
                ],
                "interior": []
            }
        },
        {
            "id": 1418440123,
            "classId": 11855359,
            "description": "36",
            "geometryType": "rectangle",
            "labelerLogin": "Item annotated with a YOLOv5l model from ultralytics trained on a custom dataset",
            "createdAt": "2023-09-21T14:49:32.964Z",
            "updatedAt": "2024-04-05T19:24:20.236593",
            "tags": [],
            "classTitle": "apple_Y5L_trained_bbox",
            "points": {
                "exterior": [
                    [
                        1035,
                        672
                    ],
                    [
                        1079,
                        715
                    ]
                ],
                "interior": []
            }
        },
        {
            "id": 1418440122,
            "classId": 11855359,
            "description": "42",
            "geometryType": "rectangle",
            "labelerLogin": "Item annotated with a YOLOv5l model from ultralytics trained on a custom dataset",
            "createdAt": "2023-09-21T14:49:32.964Z",
            "updatedAt": "2024-04-05T19:24:20.236600",
            "tags": [],
            "classTitle": "apple_Y5L_trained_bbox",
            "points": {
                "exterior": [
                    [
                        401,
                        468
                    ],
                    [
                        453,
                        519
                    ]
                ],
                "interior": []
            }
        },
        {
            "id": 1418440121,
            "classId": 11855359,
            "description": "32",
            "geometryType": "rectangle",
            "labelerLogin": "Item annotated with a YOLOv5l model from ultralytics trained on a custom dataset",
            "createdAt": "2023-09-21T14:49:32.964Z",
            "updatedAt": "2024-04-05T19:24:20.236611",
            "tags": [],
            "classTitle": "apple_Y5L_trained_bbox",
            "points": {
                "exterior": [
                    [
                        1241,
                        29
                    ],
                    [
                        1289,
                        80
                    ]
                ],
                "interior": []
            }
        }
    ]
}