{
    "description": "",
    "tags": [],
    "size": {
        "height": 1080,
        "width": 1920
    },
    "objects": [
        {
            "id": 1418435378,
            "classId": 11855358,
            "description": "34",
            "geometryType": "rectangle",
            "labelerLogin": "Gianmy12",
            "createdAt": "2023-09-21T14:48:11.307Z",
            "updatedAt": "2023-09-21T14:48:11.307Z",
            "tags": [],
            "classTitle": "Apple_Man",
            "points": {
                "exterior": [
                    [
                        1417,
                        894
                    ],
                    [
                        1527,
                        991
                    ]
                ],
                "interior": []
            }
        },
        {
            "id": 1418435413,
            "classId": 11855358,
            "description": "35",
            "geometryType": "rectangle",
            "labelerLogin": "Gianmy12",
            "createdAt": "2023-09-21T14:48:11.307Z",
            "updatedAt": "2023-09-21T14:48:11.307Z",
            "tags": [],
            "classTitle": "Apple_Man",
            "points": {
                "exterior": [
                    [
                        1096,
                        184
                    ],
                    [
                        1191,
                        268
                    ]
                ],
                "interior": []
            }
        },
        {
            "id": 1418435398,
            "classId": 11855358,
            "description": "36",
            "geometryType": "rectangle",
            "labelerLogin": "Gianmy12",
            "createdAt": "2023-09-21T14:48:11.307Z",
            "updatedAt": "2023-09-21T14:48:11.307Z",
            "tags": [],
            "classTitle": "Apple_Man",
            "points": {
                "exterior": [
                    [
                        1056,
                        514
                    ],
                    [
                        1158,
                        614
                    ]
                ],
                "interior": []
            }
        },
        {
            "id": 1418435402,
            "classId": 11855358,
            "description": "37",
            "geometryType": "rectangle",
            "labelerLogin": "Gianmy12",
            "createdAt": "2023-09-21T14:48:11.307Z",
            "updatedAt": "2023-09-21T14:48:11.307Z",
            "tags": [],
            "classTitle": "Apple_Man",
            "points": {
                "exterior": [
                    [
                        979,
                        753
                    ],
                    [
                        1071,
                        845
                    ]
                ],
                "interior": []
            }
        },
        {
            "id": 1418435370,
            "classId": 11855358,
            "description": "38",
            "geometryType": "rectangle",
            "labelerLogin": "Gianmy12",
            "createdAt": "2023-09-21T14:48:11.307Z",
            "updatedAt": "2023-09-21T14:48:11.307Z",
            "tags": [],
            "classTitle": "Apple_Man",
            "points": {
                "exterior": [
                    [
                        1040,
                        910
                    ],
                    [
                        1142,
                        1005
                    ]
                ],
                "interior": []
            }
        },
        {
            "id": 1418435390,
            "classId": 11855358,
            "description": "40",
            "geometryType": "rectangle",
            "labelerLogin": "Gianmy12",
            "createdAt": "2023-09-21T14:48:11.307Z",
            "updatedAt": "2023-09-21T14:48:11.307Z",
            "tags": [],
            "classTitle": "Apple_Man",
            "points": {
                "exterior": [
                    [
                        432,
                        722
                    ],
                    [
                        542,
                        816
                    ]
                ],
                "interior": []
            }
        },
        {
            "id": 1418435371,
            "classId": 11855358,
            "description": "43",
            "geometryType": "rectangle",
            "labelerLogin": "Gianmy12",
            "createdAt": "2023-09-21T14:48:11.307Z",
            "updatedAt": "2023-09-21T14:48:11.307Z",
            "tags": [],
            "classTitle": "Apple_Man",
            "points": {
                "exterior": [
                    [
                        152,
                        700
                    ],
                    [
                        259,
                        791
                    ]
                ],
                "interior": []
            }
        },
        {
            "id": 1418435391,
            "classId": 11855358,
            "description": "39",
            "geometryType": "rectangle",
            "labelerLogin": "Gianmy12",
            "createdAt": "2023-09-21T14:48:11.307Z",
            "updatedAt": "2023-09-21T14:48:11.307Z",
            "tags": [],
            "classTitle": "Apple_Man",
            "points": {
                "exterior": [
                    [
                        629,
                        523
                    ],
                    [
                        724,
                        615
                    ]
                ],
                "interior": []
            }
        },
        {
            "id": 1418435379,
            "classId": 11855358,
            "description": "42",
            "geometryType": "rectangle",
            "labelerLogin": "Gianmy12",
            "createdAt": "2023-09-21T14:48:11.307Z",
            "updatedAt": "2023-09-21T14:48:11.307Z",
            "tags": [],
            "classTitle": "Apple_Man",
            "points": {
                "exterior": [
                    [
                        162,
                        204
                    ],
                    [
                        284,
                        307
                    ]
                ],
                "interior": []
            }
        },
        {
            "id": 1418435418,
            "classId": 11855361,
            "description": "",
            "geometryType": "rectangle",
            "labelerLogin": "Gianmy12",
            "createdAt": "2023-09-21T14:48:11.307Z",
            "updatedAt": "2023-09-21T14:48:11.307Z",
            "tags": [],
            "classTitle": "Tennis_Man",
            "points": {
                "exterior": [
                    [
                        420,
                        204
                    ],
                    [
                        519,
                        298
                    ]
                ],
                "interior": []
            }
        },
        {
            "id": 1418435417,
            "classId": 11855361,
            "description": "",
            "geometryType": "rectangle",
            "labelerLogin": "Gianmy12",
            "createdAt": "2023-09-21T14:48:11.307Z",
            "updatedAt": "2023-09-21T14:48:11.307Z",
            "tags": [],
            "classTitle": "Tennis_Man",
            "points": {
                "exterior": [
                    [
                        918,
                        257
                    ],
                    [
                        1013,
                        352
                    ]
                ],
                "interior": []
            }
        },
        {
            "id": 1418435403,
            "classId": 11855361,
            "description": "",
            "geometryType": "rectangle",
            "labelerLogin": "Gianmy12",
            "createdAt": "2023-09-21T14:48:11.307Z",
            "updatedAt": "2023-09-21T14:48:11.307Z",
            "tags": [],
            "classTitle": "Tennis_Man",
            "points": {
                "exterior": [
                    [
                        1184,
                        864
                    ],
                    [
                        1276,
                        957
                    ]
                ],
                "interior": []
            }
        },
        {
            "id": 1418435399,
            "classId": 11855361,
            "description": "",
            "geometryType": "rectangle",
            "labelerLogin": "Gianmy12",
            "createdAt": "2023-09-21T14:48:11.307Z",
            "updatedAt": "2023-09-21T14:48:11.307Z",
            "tags": [],
            "classTitle": "Tennis_Man",
            "points": {
                "exterior": [
                    [
                        806,
                        784
                    ],
                    [
                        895,
                        874
                    ]
                ],
                "interior": []
            }
        },
        {
            "id": 1418435392,
            "classId": 11855361,
            "description": "",
            "geometryType": "rectangle",
            "labelerLogin": "Gianmy12",
            "createdAt": "2023-09-21T14:48:11.307Z",
            "updatedAt": "2023-09-21T14:48:11.307Z",
            "tags": [],
            "classTitle": "Tennis_Man",
            "points": {
                "exterior": [
                    [
                        344,
                        827
                    ],
                    [
                        443,
                        920
                    ]
                ],
                "interior": []
            }
        },
        {
            "id": 1418437731,
            "classId": 11855360,
            "description": "",
            "geometryType": "rectangle",
            "labelerLogin": "Gianmy12",
            "createdAt": "2023-09-21T14:49:03.399Z",
            "updatedAt": "2023-09-21T14:49:03.399Z",
            "tags": [],
            "classTitle": "Apple_Y5L",
            "points": {
                "exterior": [
                    [
                        819,
                        433
                    ],
                    [
                        855,
                        470
                    ]
                ],
                "interior": []
            }
        },
        {
            "id": 1418437730,
            "classId": 11855360,
            "description": "",
            "geometryType": "rectangle",
            "labelerLogin": "Gianmy12",
            "createdAt": "2023-09-21T14:49:03.399Z",
            "updatedAt": "2023-09-21T14:49:03.399Z",
            "tags": [],
            "classTitle": "Apple_Y5L",
            "points": {
                "exterior": [
                    [
                        1212,
                        534
                    ],
                    [
                        1240,
                        564
                    ]
                ],
                "interior": []
            }
        },
        {
            "id": 1418437729,
            "classId": 11855360,
            "description": "",
            "geometryType": "rectangle",
            "labelerLogin": "Gianmy12",
            "createdAt": "2023-09-21T14:49:03.399Z",
            "updatedAt": "2023-09-21T14:49:03.399Z",
            "tags": [],
            "classTitle": "Apple_Y5L",
            "points": {
                "exterior": [
                    [
                        1116,
                        476
                    ],
                    [
                        1145,
                        507
                    ]
                ],
                "interior": []
            }
        },
        {
            "id": 1418437728,
            "classId": 11855360,
            "description": "",
            "geometryType": "rectangle",
            "labelerLogin": "Gianmy12",
            "createdAt": "2023-09-21T14:49:03.399Z",
            "updatedAt": "2023-09-21T14:49:03.399Z",
            "tags": [],
            "classTitle": "Apple_Y5L",
            "points": {
                "exterior": [
                    [
                        1848,
                        932
                    ],
                    [
                        1919,
                        1030
                    ]
                ],
                "interior": []
            }
        },
        {
            "id": 1418437727,
            "classId": 11855360,
            "description": "",
            "geometryType": "rectangle",
            "labelerLogin": "Gianmy12",
            "createdAt": "2023-09-21T14:49:03.399Z",
            "updatedAt": "2023-09-21T14:49:03.399Z",
            "tags": [],
            "classTitle": "Apple_Y5L",
            "points": {
                "exterior": [
                    [
                        1117,
                        321
                    ],
                    [
                        1145,
                        364
                    ]
                ],
                "interior": []
            }
        },
        {
            "id": 1418437726,
            "classId": 11855360,
            "description": "",
            "geometryType": "rectangle",
            "labelerLogin": "Gianmy12",
            "createdAt": "2023-09-21T14:49:03.399Z",
            "updatedAt": "2023-09-21T14:49:03.399Z",
            "tags": [],
            "classTitle": "Apple_Y5L",
            "points": {
                "exterior": [
                    [
                        1445,
                        863
                    ],
                    [
                        1489,
                        900
                    ]
                ],
                "interior": []
            }
        },
        {
            "id": 1418437725,
            "classId": 11855360,
            "description": "",
            "geometryType": "rectangle",
            "labelerLogin": "Gianmy12",
            "createdAt": "2023-09-21T14:49:03.399Z",
            "updatedAt": "2023-09-21T14:49:03.399Z",
            "tags": [],
            "classTitle": "Apple_Y5L",
            "points": {
                "exterior": [
                    [
                        246,
                        825
                    ],
                    [
                        334,
                        897
                    ]
                ],
                "interior": []
            }
        },
        {
            "id": 1418437724,
            "classId": 11855360,
            "description": "",
            "geometryType": "rectangle",
            "labelerLogin": "Gianmy12",
            "createdAt": "2023-09-21T14:49:03.399Z",
            "updatedAt": "2023-09-21T14:49:03.399Z",
            "tags": [],
            "classTitle": "Apple_Y5L",
            "points": {
                "exterior": [
                    [
                        1379,
                        963
                    ],
                    [
                        1473,
                        1050
                    ]
                ],
                "interior": []
            }
        },
        {
            "id": 1418437723,
            "classId": 11855360,
            "description": "",
            "geometryType": "rectangle",
            "labelerLogin": "Gianmy12",
            "createdAt": "2023-09-21T14:49:03.399Z",
            "updatedAt": "2023-09-21T14:49:03.399Z",
            "tags": [],
            "classTitle": "Apple_Y5L",
            "points": {
                "exterior": [
                    [
                        593,
                        263
                    ],
                    [
                        652,
                        335
                    ]
                ],
                "interior": []
            }
        },
        {
            "id": 1418437722,
            "classId": 11855360,
            "description": "",
            "geometryType": "rectangle",
            "labelerLogin": "Gianmy12",
            "createdAt": "2023-09-21T14:49:03.399Z",
            "updatedAt": "2023-09-21T14:49:03.399Z",
            "tags": [],
            "classTitle": "Apple_Y5L",
            "points": {
                "exterior": [
                    [
                        199,
                        335
                    ],
                    [
                        292,
                        417
                    ]
                ],
                "interior": []
            }
        },
        {
            "id": 1418437721,
            "classId": 11855360,
            "description": "",
            "geometryType": "rectangle",
            "labelerLogin": "Gianmy12",
            "createdAt": "2023-09-21T14:49:03.399Z",
            "updatedAt": "2023-09-21T14:49:03.399Z",
            "tags": [],
            "classTitle": "Apple_Y5L",
            "points": {
                "exterior": [
                    [
                        1239,
                        0
                    ],
                    [
                        1339,
                        43
                    ]
                ],
                "interior": []
            }
        },
        {
            "id": 1418437720,
            "classId": 11855360,
            "description": "",
            "geometryType": "rectangle",
            "labelerLogin": "Gianmy12",
            "createdAt": "2023-09-21T14:49:03.399Z",
            "updatedAt": "2023-09-21T14:49:03.399Z",
            "tags": [],
            "classTitle": "Apple_Y5L",
            "points": {
                "exterior": [
                    [
                        1771,
                        125
                    ],
                    [
                        1878,
                        211
                    ]
                ],
                "interior": []
            }
        },
        {
            "id": 1418437719,
            "classId": 11855360,
            "description": "42",
            "geometryType": "rectangle",
            "labelerLogin": "Gianmy12",
            "createdAt": "2023-09-21T14:49:03.399Z",
            "updatedAt": "2023-09-21T14:49:03.399Z",
            "tags": [],
            "classTitle": "Apple_Y5L",
            "points": {
                "exterior": [
                    [
                        163,
                        205
                    ],
                    [
                        283,
                        305
                    ]
                ],
                "interior": []
            }
        },
        {
            "id": 1418437718,
            "classId": 11855360,
            "description": "",
            "geometryType": "rectangle",
            "labelerLogin": "Gianmy12",
            "createdAt": "2023-09-21T14:49:03.399Z",
            "updatedAt": "2023-09-21T14:49:03.399Z",
            "tags": [],
            "classTitle": "Apple_Y5L",
            "points": {
                "exterior": [
                    [
                        1222,
                        591
                    ],
                    [
                        1254,
                        622
                    ]
                ],
                "interior": []
            }
        },
        {
            "id": 1418437717,
            "classId": 11855360,
            "description": "",
            "geometryType": "rectangle",
            "labelerLogin": "Gianmy12",
            "createdAt": "2023-09-21T14:49:03.399Z",
            "updatedAt": "2023-09-21T14:49:03.399Z",
            "tags": [],
            "classTitle": "Apple_Y5L",
            "points": {
                "exterior": [
                    [
                        1010,
                        990
                    ],
                    [
                        1107,
                        1078
                    ]
                ],
                "interior": []
            }
        },
        {
            "id": 1418437716,
            "classId": 11855360,
            "description": "38",
            "geometryType": "rectangle",
            "labelerLogin": "Gianmy12",
            "createdAt": "2023-09-21T14:49:03.399Z",
            "updatedAt": "2023-09-21T14:49:03.399Z",
            "tags": [],
            "classTitle": "Apple_Y5L",
            "points": {
                "exterior": [
                    [
                        1041,
                        911
                    ],
                    [
                        1142,
                        1005
                    ]
                ],
                "interior": []
            }
        },
        {
            "id": 1418437715,
            "classId": 11855360,
            "description": "",
            "geometryType": "rectangle",
            "labelerLogin": "Gianmy12",
            "createdAt": "2023-09-21T14:49:03.399Z",
            "updatedAt": "2023-09-21T14:49:03.399Z",
            "tags": [],
            "classTitle": "Tennis_Y5L",
            "points": {
                "exterior": [
                    [
                        421,
                        205
                    ],
                    [
                        520,
                        296
                    ]
                ],
                "interior": []
            }
        },
        {
            "id": 1418437714,
            "classId": 11855360,
            "description": "",
            "geometryType": "rectangle",
            "labelerLogin": "Gianmy12",
            "createdAt": "2023-09-21T14:49:03.399Z",
            "updatedAt": "2023-09-21T14:49:03.399Z",
            "tags": [],
            "classTitle": "Apple_Y5L",
            "points": {
                "exterior": [
                    [
                        979,
                        875
                    ],
                    [
                        1066,
                        968
                    ]
                ],
                "interior": []
            }
        },
        {
            "id": 1418437713,
            "classId": 11855360,
            "description": "",
            "geometryType": "rectangle",
            "labelerLogin": "Gianmy12",
            "createdAt": "2023-09-21T14:49:03.399Z",
            "updatedAt": "2023-09-21T14:49:03.399Z",
            "tags": [],
            "classTitle": "Tennis_Y5L",
            "points": {
                "exterior": [
                    [
                        918,
                        257
                    ],
                    [
                        1013,
                        350
                    ]
                ],
                "interior": []
            }
        },
        {
            "id": 1418437712,
            "classId": 11855360,
            "description": "40",
            "geometryType": "rectangle",
            "labelerLogin": "Gianmy12",
            "createdAt": "2023-09-21T14:49:03.399Z",
            "updatedAt": "2023-09-21T14:49:03.399Z",
            "tags": [],
            "classTitle": "Apple_Y5L",
            "points": {
                "exterior": [
                    [
                        433,
                        723
                    ],
                    [
                        541,
                        814
                    ]
                ],
                "interior": []
            }
        },
        {
            "id": 1418437711,
            "classId": 11855360,
            "description": "",
            "geometryType": "rectangle",
            "labelerLogin": "Gianmy12",
            "createdAt": "2023-09-21T14:49:03.399Z",
            "updatedAt": "2023-09-21T14:49:03.399Z",
            "tags": [],
            "classTitle": "Tennis_Y5L",
            "points": {
                "exterior": [
                    [
                        344,
                        826
                    ],
                    [
                        441,
                        920
                    ]
                ],
                "interior": []
            }
        },
        {
            "id": 1418437710,
            "classId": 11855360,
            "description": "",
            "geometryType": "rectangle",
            "labelerLogin": "Gianmy12",
            "createdAt": "2023-09-21T14:49:03.399Z",
            "updatedAt": "2023-09-21T14:49:03.399Z",
            "tags": [],
            "classTitle": "Apple_Y5L",
            "points": {
                "exterior": [
                    [
                        1751,
                        225
                    ],
                    [
                        1858,
                        311
                    ]
                ],
                "interior": []
            }
        },
        {
            "id": 1418437709,
            "classId": 11855360,
            "description": "",
            "geometryType": "rectangle",
            "labelerLogin": "Gianmy12",
            "createdAt": "2023-09-21T14:49:03.399Z",
            "updatedAt": "2023-09-21T14:49:03.399Z",
            "tags": [],
            "classTitle": "Apple_Y5L",
            "points": {
                "exterior": [
                    [
                        212,
                        420
                    ],
                    [
                        314,
                        507
                    ]
                ],
                "interior": []
            }
        },
        {
            "id": 1418437708,
            "classId": 11855360,
            "description": "",
            "geometryType": "rectangle",
            "labelerLogin": "Gianmy12",
            "createdAt": "2023-09-21T14:49:03.399Z",
            "updatedAt": "2023-09-21T14:49:03.399Z",
            "tags": [],
            "classTitle": "Tennis_Y5L",
            "points": {
                "exterior": [
                    [
                        1185,
                        865
                    ],
                    [
                        1273,
                        957
                    ]
                ],
                "interior": []
            }
        },
        {
            "id": 1418437707,
            "classId": 11855360,
            "description": "36",
            "geometryType": "rectangle",
            "labelerLogin": "Gianmy12",
            "createdAt": "2023-09-21T14:49:03.399Z",
            "updatedAt": "2023-09-21T14:49:03.399Z",
            "tags": [],
            "classTitle": "Apple_Y5L",
            "points": {
                "exterior": [
                    [
                        1060,
                        514
                    ],
                    [
                        1157,
                        615
                    ]
                ],
                "interior": []
            }
        },
        {
            "id": 1418437706,
            "classId": 11855360,
            "description": "",
            "geometryType": "rectangle",
            "labelerLogin": "Gianmy12",
            "createdAt": "2023-09-21T14:49:03.399Z",
            "updatedAt": "2023-09-21T14:49:03.399Z",
            "tags": [],
            "classTitle": "Tennis_Y5L",
            "points": {
                "exterior": [
                    [
                        809,
                        784
                    ],
                    [
                        893,
                        871
                    ]
                ],
                "interior": []
            }
        },
        {
            "id": 1418437705,
            "classId": 11855360,
            "description": "34",
            "geometryType": "rectangle",
            "labelerLogin": "Gianmy12",
            "createdAt": "2023-09-21T14:49:03.399Z",
            "updatedAt": "2023-09-21T14:49:03.399Z",
            "tags": [],
            "classTitle": "Apple_Y5L",
            "points": {
                "exterior": [
                    [
                        1419,
                        895
                    ],
                    [
                        1525,
                        990
                    ]
                ],
                "interior": []
            }
        },
        {
            "id": 1418437704,
            "classId": 11855360,
            "description": "37",
            "geometryType": "rectangle",
            "labelerLogin": "Gianmy12",
            "createdAt": "2023-09-21T14:49:03.399Z",
            "updatedAt": "2023-09-21T14:49:03.399Z",
            "tags": [],
            "classTitle": "Apple_Y5L",
            "points": {
                "exterior": [
                    [
                        983,
                        754
                    ],
                    [
                        1072,
                        844
                    ]
                ],
                "interior": []
            }
        },
        {
            "id": 1418437703,
            "classId": 11855360,
            "description": "",
            "geometryType": "rectangle",
            "labelerLogin": "Gianmy12",
            "createdAt": "2023-09-21T14:49:03.399Z",
            "updatedAt": "2023-09-21T14:49:03.399Z",
            "tags": [],
            "classTitle": "Apple_Y5L",
            "points": {
                "exterior": [
                    [
                        311,
                        474
                    ],
                    [
                        405,
                        572
                    ]
                ],
                "interior": []
            }
        },
        {
            "id": 1418437702,
            "classId": 11855360,
            "description": "43",
            "geometryType": "rectangle",
            "labelerLogin": "Gianmy12",
            "createdAt": "2023-09-21T14:49:03.399Z",
            "updatedAt": "2023-09-21T14:49:03.399Z",
            "tags": [],
            "classTitle": "Apple_Y5L",
            "points": {
                "exterior": [
                    [
                        154,
                        701
                    ],
                    [
                        258,
                        791
                    ]
                ],
                "interior": []
            }
        },
        {
            "id": 1418437701,
            "classId": 11855360,
            "description": "39",
            "geometryType": "rectangle",
            "labelerLogin": "Gianmy12",
            "createdAt": "2023-09-21T14:49:03.399Z",
            "updatedAt": "2023-09-21T14:49:03.399Z",
            "tags": [],
            "classTitle": "Apple_Y5L",
            "points": {
                "exterior": [
                    [
                        631,
                        524
                    ],
                    [
                        722,
                        615
                    ]
                ],
                "interior": []
            }
        },
        {
            "id": 1418437700,
            "classId": 11855360,
            "description": "35",
            "geometryType": "rectangle",
            "labelerLogin": "Gianmy12",
            "createdAt": "2023-09-21T14:49:03.399Z",
            "updatedAt": "2023-09-21T14:49:03.399Z",
            "tags": [],
            "classTitle": "Apple_Y5L",
            "points": {
                "exterior": [
                    [
                        1099,
                        184
                    ],
                    [
                        1191,
                        268
                    ]
                ],
                "interior": []
            }
        },
        {
            "id": 1418439748,
            "classId": 11855359,
            "description": "",
            "geometryType": "rectangle",
            "labelerLogin": "Gianmy12",
            "createdAt": "2023-09-21T14:49:32.963Z",
            "updatedAt": "2023-09-21T14:49:32.963Z",
            "tags": [],
            "classTitle": "Tennis_ourY5L",
            "points": {
                "exterior": [
                    [
                        424,
                        206
                    ],
                    [
                        517,
                        295
                    ]
                ],
                "interior": []
            }
        },
        {
            "id": 1418439747,
            "classId": 11855359,
            "description": "",
            "geometryType": "rectangle",
            "labelerLogin": "Gianmy12",
            "createdAt": "2023-09-21T14:49:32.963Z",
            "updatedAt": "2023-09-21T14:49:32.963Z",
            "tags": [],
            "classTitle": "Apple_ourY5L",
            "points": {
                "exterior": [
                    [
                        588,
                        263
                    ],
                    [
                        655,
                        335
                    ]
                ],
                "interior": []
            }
        },
        {
            "id": 1418439746,
            "classId": 11855359,
            "description": "",
            "geometryType": "rectangle",
            "labelerLogin": "Gianmy12",
            "createdAt": "2023-09-21T14:49:32.963Z",
            "updatedAt": "2023-09-21T14:49:32.963Z",
            "tags": [],
            "classTitle": "Tennis_ourY5L",
            "points": {
                "exterior": [
                    [
                        808,
                        784
                    ],
                    [
                        896,
                        870
                    ]
                ],
                "interior": []
            }
        },
        {
            "id": 1418439745,
            "classId": 11855359,
            "description": "",
            "geometryType": "rectangle",
            "labelerLogin": "Gianmy12",
            "createdAt": "2023-09-21T14:49:32.963Z",
            "updatedAt": "2023-09-21T14:49:32.963Z",
            "tags": [],
            "classTitle": "Apple_ourY5L",
            "points": {
                "exterior": [
                    [
                        1857,
                        62
                    ],
                    [
                        1919,
                        161
                    ]
                ],
                "interior": []
            }
        },
        {
            "id": 1418439744,
            "classId": 11855359,
            "description": "",
            "geometryType": "rectangle",
            "labelerLogin": "Gianmy12",
            "createdAt": "2023-09-21T14:49:32.963Z",
            "updatedAt": "2023-09-21T14:49:32.963Z",
            "tags": [],
            "classTitle": "Apple_ourY5L",
            "points": {
                "exterior": [
                    [
                        1240,
                        0
                    ],
                    [
                        1342,
                        42
                    ]
                ],
                "interior": []
            }
        },
        {
            "id": 1418439743,
            "classId": 11855359,
            "description": "",
            "geometryType": "rectangle",
            "labelerLogin": "Gianmy12",
            "createdAt": "2023-09-21T14:49:32.963Z",
            "updatedAt": "2023-09-21T14:49:32.963Z",
            "tags": [],
            "classTitle": "Tennis_ourY5L",
            "points": {
                "exterior": [
                    [
                        919,
                        257
                    ],
                    [
                        998,
                        347
                    ]
                ],
                "interior": []
            }
        },
        {
            "id": 1418439742,
            "classId": 11855359,
            "description": "",
            "geometryType": "rectangle",
            "labelerLogin": "Gianmy12",
            "createdAt": "2023-09-21T14:49:32.963Z",
            "updatedAt": "2023-09-21T14:49:32.963Z",
            "tags": [],
            "classTitle": "Apple_ourY5L",
            "points": {
                "exterior": [
                    [
                        1756,
                        223
                    ],
                    [
                        1858,
                        312
                    ]
                ],
                "interior": []
            }
        },
        {
            "id": 1418439741,
            "classId": 11855359,
            "description": "",
            "geometryType": "rectangle",
            "labelerLogin": "Gianmy12",
            "createdAt": "2023-09-21T14:49:32.963Z",
            "updatedAt": "2023-09-21T14:49:32.963Z",
            "tags": [],
            "classTitle": "Apple_ourY5L",
            "points": {
                "exterior": [
                    [
                        981,
                        875
                    ],
                    [
                        1065,
                        965
                    ]
                ],
                "interior": []
            }
        },
        {
            "id": 1418439740,
            "classId": 11855359,
            "description": "37",
            "geometryType": "rectangle",
            "labelerLogin": "Gianmy12",
            "createdAt": "2023-09-21T14:49:32.963Z",
            "updatedAt": "2023-09-21T14:49:32.963Z",
            "tags": [],
            "classTitle": "Apple_ourY5L",
            "points": {
                "exterior": [
                    [
                        981,
                        753
                    ],
                    [
                        1072,
                        842
                    ]
                ],
                "interior": []
            }
        },
        {
            "id": 1418439739,
            "classId": 11855359,
            "description": "",
            "geometryType": "rectangle",
            "labelerLogin": "Gianmy12",
            "createdAt": "2023-09-21T14:49:32.963Z",
            "updatedAt": "2023-09-21T14:49:32.963Z",
            "tags": [],
            "classTitle": "Apple_ourY5L",
            "points": {
                "exterior": [
                    [
                        1772,
                        126
                    ],
                    [
                        1877,
                        207
                    ]
                ],
                "interior": []
            }
        },
        {
            "id": 1418439738,
            "classId": 11855359,
            "description": "",
            "geometryType": "rectangle",
            "labelerLogin": "Gianmy12",
            "createdAt": "2023-09-21T14:49:32.963Z",
            "updatedAt": "2023-09-21T14:49:32.963Z",
            "tags": [],
            "classTitle": "Apple_ourY5L",
            "points": {
                "exterior": [
                    [
                        1011,
                        992
                    ],
                    [
                        1105,
                        1079
                    ]
                ],
                "interior": []
            }
        },
        {
            "id": 1418439737,
            "classId": 11855359,
            "description": "43",
            "geometryType": "rectangle",
            "labelerLogin": "Gianmy12",
            "createdAt": "2023-09-21T14:49:32.963Z",
            "updatedAt": "2023-09-21T14:49:32.963Z",
            "tags": [],
            "classTitle": "Apple_ourY5L",
            "points": {
                "exterior": [
                    [
                        152,
                        701
                    ],
                    [
                        256,
                        791
                    ]
                ],
                "interior": []
            }
        },
        {
            "id": 1418439736,
            "classId": 11855359,
            "description": "",
            "geometryType": "rectangle",
            "labelerLogin": "Gianmy12",
            "createdAt": "2023-09-21T14:49:32.963Z",
            "updatedAt": "2023-09-21T14:49:32.963Z",
            "tags": [],
            "classTitle": "Apple_ourY5L",
            "points": {
                "exterior": [
                    [
                        313,
                        475
                    ],
                    [
                        406,
                        571
                    ]
                ],
                "interior": []
            }
        },
        {
            "id": 1418439735,
            "classId": 11855359,
            "description": "38",
            "geometryType": "rectangle",
            "labelerLogin": "Gianmy12",
            "createdAt": "2023-09-21T14:49:32.963Z",
            "updatedAt": "2023-09-21T14:49:32.963Z",
            "tags": [],
            "classTitle": "Apple_ourY5L",
            "points": {
                "exterior": [
                    [
                        1043,
                        911
                    ],
                    [
                        1142,
                        1004
                    ]
                ],
                "interior": []
            }
        },
        {
            "id": 1418439734,
            "classId": 11855359,
            "description": "42",
            "geometryType": "rectangle",
            "labelerLogin": "Gianmy12",
            "createdAt": "2023-09-21T14:49:32.963Z",
            "updatedAt": "2023-09-21T14:49:32.963Z",
            "tags": [],
            "classTitle": "Apple_ourY5L",
            "points": {
                "exterior": [
                    [
                        167,
                        208
                    ],
                    [
                        278,
                        304
                    ]
                ],
                "interior": []
            }
        },
        {
            "id": 1418439733,
            "classId": 11855359,
            "description": "39",
            "geometryType": "rectangle",
            "labelerLogin": "Gianmy12",
            "createdAt": "2023-09-21T14:49:32.963Z",
            "updatedAt": "2023-09-21T14:49:32.963Z",
            "tags": [],
            "classTitle": "Apple_ourY5L",
            "points": {
                "exterior": [
                    [
                        634,
                        525
                    ],
                    [
                        721,
                        611
                    ]
                ],
                "interior": []
            }
        },
        {
            "id": 1418439732,
            "classId": 11855359,
            "description": "",
            "geometryType": "rectangle",
            "labelerLogin": "Gianmy12",
            "createdAt": "2023-09-21T14:49:32.963Z",
            "updatedAt": "2023-09-21T14:49:32.963Z",
            "tags": [],
            "classTitle": "Tennis_ourY5L",
            "points": {
                "exterior": [
                    [
                        352,
                        827
                    ],
                    [
                        442,
                        918
                    ]
                ],
                "interior": []
            }
        },
        {
            "id": 1418439731,
            "classId": 11855359,
            "description": "40",
            "geometryType": "rectangle",
            "labelerLogin": "Gianmy12",
            "createdAt": "2023-09-21T14:49:32.963Z",
            "updatedAt": "2023-09-21T14:49:32.963Z",
            "tags": [],
            "classTitle": "Apple_ourY5L",
            "points": {
                "exterior": [
                    [
                        433,
                        723
                    ],
                    [
                        540,
                        818
                    ]
                ],
                "interior": []
            }
        },
        {
            "id": 1418439730,
            "classId": 11855359,
            "description": "",
            "geometryType": "rectangle",
            "labelerLogin": "Gianmy12",
            "createdAt": "2023-09-21T14:49:32.963Z",
            "updatedAt": "2023-09-21T14:49:32.963Z",
            "tags": [],
            "classTitle": "Tennis_ourY5L",
            "points": {
                "exterior": [
                    [
                        1183,
                        866
                    ],
                    [
                        1275,
                        956
                    ]
                ],
                "interior": []
            }
        },
        {
            "id": 1418439729,
            "classId": 11855359,
            "description": "36",
            "geometryType": "rectangle",
            "labelerLogin": "Gianmy12",
            "createdAt": "2023-09-21T14:49:32.963Z",
            "updatedAt": "2023-09-21T14:49:32.963Z",
            "tags": [],
            "classTitle": "Apple_ourY5L",
            "points": {
                "exterior": [
                    [
                        1059,
                        513
                    ],
                    [
                        1157,
                        611
                    ]
                ],
                "interior": []
            }
        },
        {
            "id": 1418439728,
            "classId": 11855359,
            "description": "34",
            "geometryType": "rectangle",
            "labelerLogin": "Gianmy12",
            "createdAt": "2023-09-21T14:49:32.963Z",
            "updatedAt": "2023-09-21T14:49:32.963Z",
            "tags": [],
            "classTitle": "Apple_ourY5L",
            "points": {
                "exterior": [
                    [
                        1419,
                        895
                    ],
                    [
                        1527,
                        989
                    ]
                ],
                "interior": []
            }
        },
        {
            "id": 1418439727,
            "classId": 11855359,
            "description": "",
            "geometryType": "rectangle",
            "labelerLogin": "Gianmy12",
            "createdAt": "2023-09-21T14:49:32.963Z",
            "updatedAt": "2023-09-21T14:49:32.963Z",
            "tags": [],
            "classTitle": "Apple_ourY5L",
            "points": {
                "exterior": [
                    [
                        209,
                        420
                    ],
                    [
                        314,
                        507
                    ]
                ],
                "interior": []
            }
        },
        {
            "id": 1418439726,
            "classId": 11855359,
            "description": "35",
            "geometryType": "rectangle",
            "labelerLogin": "Gianmy12",
            "createdAt": "2023-09-21T14:49:32.963Z",
            "updatedAt": "2023-09-21T14:49:32.963Z",
            "tags": [],
            "classTitle": "Apple_ourY5L",
            "points": {
                "exterior": [
                    [
                        1098,
                        183
                    ],
                    [
                        1191,
                        266
                    ]
                ],
                "interior": []
            }
        }
    ]
}